zwnlptk/__init__.py
zwnlptk/__version__.py
zwnlptk/souputils.py
zwnlptk-0.0.1.dist-info/LICENSE
zwnlptk-0.0.1.dist-info/METADATA
zwnlptk-0.0.1.dist-info/WHEEL
zwnlptk-0.0.1.dist-info/top_level.txt
zwnlptk-0.0.1.dist-info/RECORD
