Metadata-Version: 2.1
Name: zwnlptk
Version: 0.0.1
Summary: Personal nlp utils.
Home-page: https://github.com/njzhaowei/zwnlptk
Author: Zhao Wei
Author-email: yewberry@163.com
License: Apache 2.0
Platform: all
Classifier: Programming Language :: Python :: 3
Classifier: License :: OSI Approved :: Apache Software License
Classifier: Operating System :: OS Independent
Requires-Python: >=3.6
Requires-Dist: beautifulsoup4
Requires-Dist: lxml
Requires-Dist: jieba
